pykawa/__init__.py
pykawa-0.1.dist-info/LICENCE.txt
pykawa-0.1.dist-info/METADATA
pykawa-0.1.dist-info/WHEEL
pykawa-0.1.dist-info/top_level.txt
pykawa-0.1.dist-info/RECORD
