Metadata-Version: 2.1
Name: pykawa
Version: 0.1
Summary: Helpers
Home-page: https://github.com/araamouch/pydaa
Author: Araamouch
Classifier: Programming Language :: Python :: 3
Classifier: License :: OSI Approved :: MIT License
Classifier: Operating System :: OS Independent
Requires-Python: >=3.6
License-File: LICENCE.txt
